[{"firstImage":"https://cloudinary.images-iherb.com/image/upload/f_auto,q_auto:eco/images/wsh/wsh95370/u/27.jpg","popularity":0,"productUrl":"https://www.iherb.com/pr/9wishes-sun-moisturizer-spf-50-pa-1-7-fl-oz-50-ml/90613","title":"9Wishes, Sun Moisturizer, SPF 50+ PA+++, 1.7 fl oz (50 ml)","weight":"0.08 kg","quantity":"50.27 ml","priceUs":"$20.99","dimensions":"12.7 x 5.1 x 3.3 cm, 0.07 kg","expiryDate":"April 2026","rating":"2,580"},{"firstImage":"https://cloudinary.images-iherb.com/image/upload/f_auto,q_auto:eco/images/wsh/wsh95441/u/30.jpg","popularity":1,"productUrl":"https://www.iherb.com/pr/9wishes-rice-foaming-cleanser-4-fl-oz-120-ml/90607","title":"9Wishes, Rice Foaming Cleanser, 4 fl oz (120 ml)","weight":"0.15 kg","quantity":"118.29 ml","priceUs":"$18.99","dimensions":"17.5 x 5.1 x 4.1 cm, 0.15 kg","expiryDate":"May 2026","rating":"285"},{"firstImage":"https://cloudinary.images-iherb.com/image/upload/f_auto,q_auto:eco/images/wsh/wsh95820/u/10.jpg","popularity":2,"productUrl":"https://www.iherb.com/pr/9wishes-pine-lightweight-sunscreen-spf50-pa-1-7-fl-oz-50-ml/114672","title":"9Wishes, Pine, Lightweight Sunscreen, SPF50+PA++++, 1.7 fl oz (50 ml)","weight":"0.07 kg","quantity":"50.27 ml","priceUs":"$17.60","dimensions":"12.7 x 5.2 x 3 cm, 0.07 kg","expiryDate":"February 2026","rating":"193"},{"firstImage":"https://cloudinary.images-iherb.com/image/upload/f_auto,q_auto:eco/images/wsh/wsh76955/u/9.jpg","popularity":3,"productUrl":"https://www.iherb.com/pr/9wishes-white-lucent-refining-toner-5-1-fl-oz-150-ml/116990","title":"9Wishes, White Lucent Refining Toner, 5.1 fl oz (150 ml)","weight":"0.25 kg","quantity":"150.82 ml","priceUs":"$15.95","dimensions":"18.8 x 4.8 x 4.6 cm, 0.25 kg","expiryDate":"May 2026","rating":"16"},{"firstImage":"https://cloudinary.images-iherb.com/image/upload/f_auto,q_auto:eco/images/wsh/wsh95392/u/11.jpg","popularity":4,"productUrl":"https://www.iherb.com/pr/9wishes-rice-radiance-cream-1-7-fl-oz-50-ml/116992","title":"9Wishes, Rice Radiance Cream, 1.7 fl oz (50 ml)","weight":"0.21 kg","quantity":"50.27 ml","priceUs":"$19.10","dimensions":"6.7 x 6.6 x 5.8 cm, 0.21 kg","expiryDate":"August 2026","rating":"18"},{"firstImage":"https://cloudinary.images-iherb.com/image/upload/f_auto,q_auto:eco/images/wsh/wsh95150/u/9.jpg","popularity":5,"productUrl":"https://www.iherb.com/pr/9wishes-white-lucent-serum-1-7-fl-oz-50-ml/116989","title":"9Wishes, White Lucent Serum, 1.7 fl oz (50  ml)","weight":"0.12 kg","quantity":"50.27 ml","priceUs":"$16.80","dimensions":"12.3 x 3.9 x 3.9 cm, 0.12 kg","expiryDate":"August 2026","rating":"13"},{"popularity":6,"productUrl":"https://www.iherb.com/pr/9wishes-pine-ampule-serum-0-85-fl-oz-25-ml/114671","title":"9Wishes, Pine, Ampule Serum, 0.85 fl oz (25 ml)","weight":"0.09 kg","quantity":"25.14 ml","priceUs":"$21.60","dimensions":"10.9 x 3.7 x 3.4 cm, 0.09 kg","expiryDate":"August 2025","rating":"255"},{"popularity":7,"productUrl":"https://www.iherb.com/pr/9wishes-ampule-serum-calm-0-85-fl-oz-25-ml/90319","title":"9Wishes, Ampule Serum, Calm, 0.85 fl oz (25 ml)","weight":"0.09 kg","quantity":"25.14 ml","priceUs":"$12.00","dimensions":"10.9 x 3.7 x 3.6 cm, 0.09 kg","expiryDate":"January 2026","rating":"41"},{"popularity":8,"productUrl":"https://www.iherb.com/pr/9wishes-propolis-extract-81-1-fl-oz-30-ml/116991","title":"9Wishes, Propolis Extract 81%, 1 fl oz (30 ml)","weight":"0.14 kg","quantity":"29.57 ml","priceUs":"$20.30","dimensions":"10.7 x 4.7 x 4.7 cm, 0.14 kg","expiryDate":"December 2025","rating":"8"},{"firstImage":"https://cloudinary.images-iherb.com/image/upload/f_auto,q_auto:eco/images/wsh/wsh95370/u/27.jpg","popularity":0,"productUrl":"https://www.iherb.com/pr/9wishes-sun-moisturizer-spf-50-pa-1-7-fl-oz-50-ml/90613","title":"9Wishes, Sun Moisturizer, SPF 50+ PA+++, 1.7 fl oz (50 ml)","weight":"0.08 kg","quantity":"50.27 ml","priceUs":"$20.99","dimensions":"12.7 x 5.1 x 3.3 cm, 0.07 kg","expiryDate":"undefined undefined","rating":"2,580"},{"firstImage":"https://cloudinary.images-iherb.com/image/upload/f_auto,q_auto:eco/images/wsh/wsh95441/u/30.jpg","popularity":1,"productUrl":"https://www.iherb.com/pr/9wishes-rice-foaming-cleanser-4-fl-oz-120-ml/90607","title":"9Wishes, Rice Foaming Cleanser, 4 fl oz (120 ml)","weight":"0.15 kg","quantity":"118.29 ml","priceUs":"$18.99","dimensions":"17.5 x 5.1 x 4.1 cm, 0.15 kg","expiryDate":"undefined undefined","rating":"285"},{"firstImage":"https://cloudinary.images-iherb.com/image/upload/f_auto,q_auto:eco/images/wsh/wsh95820/u/10.jpg","popularity":2,"productUrl":"https://www.iherb.com/pr/9wishes-pine-lightweight-sunscreen-spf50-pa-1-7-fl-oz-50-ml/114672","title":"9Wishes, Pine, Lightweight Sunscreen, SPF50+PA++++, 1.7 fl oz (50 ml)","weight":"0.07 kg","quantity":"50.27 ml","priceUs":"$17.60","dimensions":"12.7 x 5.2 x 3 cm, 0.07 kg","expiryDate":"undefined undefined","rating":"193"},{"firstImage":"https://cloudinary.images-iherb.com/image/upload/f_auto,q_auto:eco/images/wsh/wsh76955/u/9.jpg","popularity":3,"productUrl":"https://www.iherb.com/pr/9wishes-white-lucent-refining-toner-5-1-fl-oz-150-ml/116990","title":"9Wishes, White Lucent Refining Toner, 5.1 fl oz (150 ml)","weight":"0.25 kg","quantity":"150.82 ml","priceUs":"$15.95","dimensions":"18.8 x 4.8 x 4.6 cm, 0.25 kg","expiryDate":"undefined undefined","rating":"16"},{"firstImage":"https://cloudinary.images-iherb.com/image/upload/f_auto,q_auto:eco/images/wsh/wsh95392/u/11.jpg","popularity":4,"productUrl":"https://www.iherb.com/pr/9wishes-rice-radiance-cream-1-7-fl-oz-50-ml/116992","title":"9Wishes, Rice Radiance Cream, 1.7 fl oz (50 ml)","weight":"0.21 kg","quantity":"50.27 ml","priceUs":"$19.10","dimensions":"6.7 x 6.6 x 5.8 cm, 0.21 kg","expiryDate":"undefined undefined","rating":"18"},{"firstImage":"https://cloudinary.images-iherb.com/image/upload/f_auto,q_auto:eco/images/wsh/wsh95150/u/9.jpg","popularity":5,"productUrl":"https://www.iherb.com/pr/9wishes-white-lucent-serum-1-7-fl-oz-50-ml/116989","title":"9Wishes, White Lucent Serum, 1.7 fl oz (50  ml)","weight":"0.12 kg","quantity":"50.27 ml","priceUs":"$16.80","dimensions":"12.3 x 3.9 x 3.9 cm, 0.12 kg","expiryDate":"undefined undefined","rating":"13"},{"firstImage":"https://cloudinary.images-iherb.com/image/upload/f_auto,q_auto:eco/images/dzc/dzc03047/u/2.jpg","popularity":6,"productUrl":"https://www.iherb.com/pr/9wishes-pine-ampule-serum-0-85-fl-oz-25-ml/114671","title":"9Wishes, Pine, Ampule Serum, 0.85 fl oz (25 ml)","weight":"0.09 kg","quantity":"25.14 ml","priceUs":"$21.60","dimensions":"10.9 x 3.7 x 3.4 cm, 0.09 kg","expiryDate":"undefined undefined","rating":"255"},{"firstImage":"https://cloudinary.images-iherb.com/image/upload/f_auto,q_auto:eco/images/dzc/dzc03024/u/2.jpg","popularity":7,"productUrl":"https://www.iherb.com/pr/9wishes-ampule-serum-calm-0-85-fl-oz-25-ml/90319","title":"9Wishes, Ampule Serum, Calm, 0.85 fl oz (25 ml)","weight":"0.09 kg","quantity":"25.14 ml","priceUs":"$12.00","dimensions":"10.9 x 3.7 x 3.6 cm, 0.09 kg","expiryDate":"undefined undefined","rating":"41"},{"firstImage":"https://cloudinary.images-iherb.com/image/upload/f_auto,q_auto:eco/images/dzc/dzc03049/u/2.jpg","popularity":8,"productUrl":"https://www.iherb.com/pr/9wishes-propolis-extract-81-1-fl-oz-30-ml/116991","title":"9Wishes, Propolis Extract 81%, 1 fl oz (30 ml)","weight":"0.14 kg","quantity":"29.57 ml","priceUs":"$20.30","dimensions":"10.7 x 4.7 x 4.7 cm, 0.14 kg","expiryDate":"undefined undefined","rating":"8"},{"firstImage":"https://cloudinary.images-iherb.com/image/upload/f_auto,q_auto:eco/images/dzc/dzc03048/u/2.jpg","popularity":9,"productUrl":"https://www.iherb.com/pr/a-dozen-cousins-jamaican-jerk-seasoning-medium-3-oz-85-g/116411","title":"A Dozen Cousins, Jamaican Jerk Seasoning, Medium, 3 oz (85 g)","weight":"0.09 kg","quantity":"85.05 g","priceUs":"$3.61","dimensions":"12.3 x 6.6 x 3.2 cm, 0.09 kg","expiryDate":"April 2025","rating":"34"},{"firstImage":"https://cloudinary.images-iherb.com/image/upload/f_auto,q_auto:eco/images/dzc/dzc03002/u/2.jpg","popularity":10,"productUrl":"https://www.iherb.com/pr/a-dozen-cousins-caribbean-coconut-rice-seasoning-sauce-4-oz-113/116398","title":"A Dozen Cousins, Caribbean Coconut Rice, Seasoning Sauce, 4 oz (113)","weight":"0.13 kg","quantity":"113.4 g","priceUs":"$3.61","dimensions":"12.4 x 7.2 x 5.5 cm, 0.12 kg","expiryDate":"October 2024","rating":"23"},{"popularity":11,"productUrl":"https://www.iherb.com/pr/a-dozen-cousins-peruvian-pollo-a-la-brasa-seasoning-sauce-mild-3-oz-85-g/116414","title":"A Dozen Cousins, Peruvian Pollo A La Brasa, Seasoning Sauce, Mild, 3 oz (85 g)","weight":"0.1 kg","quantity":"85.05 g","priceUs":"$3.61","dimensions":"12.6 x 7.2 x 2.9 cm, 0.1 kg","expiryDate":"April 2025","rating":"29"},{"popularity":12,"productUrl":"https://www.iherb.com/pr/a-dozen-cousins-mexican-pollo-asado-seasoning-sauce-3-oz-85-g/116415","title":"A Dozen Cousins, Mexican Pollo Asado Seasoning Sauce, 3 oz (85 g)","weight":"0.09 kg","quantity":"85.05 g","priceUs":"$3.61","dimensions":"12.6 x 7.1 x 2.9 cm, 0.09 kg","expiryDate":"January 2025","rating":"48"},{"popularity":13,"productUrl":"https://www.iherb.com/pr/a-dozen-cousins-trini-chickpea-curry-mild-10-oz-283-g/116399","title":"A Dozen Cousins, Trini Chickpea Curry, Mild, 10 oz (283 g)","weight":"0.29 kg","quantity":"283.5 g","priceUs":"$4.51","dimensions":"13.6 x 9.8 x 6.9 cm, 0.29 kg","expiryDate":"January 2024","rating":"9"},{"firstImage":"https://cloudinary.images-iherb.com/image/upload/f_auto,q_auto:eco/images/wsh/wsh95370/u/27.jpg","popularity":0,"productUrl":"https://www.iherb.com/pr/9wishes-sun-moisturizer-spf-50-pa-1-7-fl-oz-50-ml/90613","title":"9Wishes, Sun Moisturizer, SPF 50+ PA+++, 1.7 fl oz (50 ml)","weight":"0.08 kg","quantity":"50.27 ml","priceUs":"$20.99","dimensions":"12.7 x 5.1 x 3.3 cm, 0.07 kg","expiryDate":"undefined undefined","rating":"2,580"},{"firstImage":"https://cloudinary.images-iherb.com/image/upload/f_auto,q_auto:eco/images/wsh/wsh95441/u/30.jpg","popularity":1,"productUrl":"https://www.iherb.com/pr/9wishes-rice-foaming-cleanser-4-fl-oz-120-ml/90607","title":"9Wishes, Rice Foaming Cleanser, 4 fl oz (120 ml)","weight":"0.15 kg","quantity":"118.29 ml","priceUs":"$18.99","dimensions":"17.5 x 5.1 x 4.1 cm, 0.15 kg","expiryDate":"undefined undefined","rating":"285"},{"firstImage":"https://cloudinary.images-iherb.com/image/upload/f_auto,q_auto:eco/images/wsh/wsh95820/u/10.jpg","popularity":2,"productUrl":"https://www.iherb.com/pr/9wishes-pine-lightweight-sunscreen-spf50-pa-1-7-fl-oz-50-ml/114672","title":"9Wishes, Pine, Lightweight Sunscreen, SPF50+PA++++, 1.7 fl oz (50 ml)","weight":"0.07 kg","quantity":"50.27 ml","priceUs":"$17.60","dimensions":"12.7 x 5.2 x 3 cm, 0.07 kg","expiryDate":"undefined undefined","rating":"193"},{"firstImage":"https://cloudinary.images-iherb.com/image/upload/f_auto,q_auto:eco/images/wsh/wsh76955/u/9.jpg","popularity":3,"productUrl":"https://www.iherb.com/pr/9wishes-white-lucent-refining-toner-5-1-fl-oz-150-ml/116990","title":"9Wishes, White Lucent Refining Toner, 5.1 fl oz (150 ml)","weight":"0.25 kg","quantity":"150.82 ml","priceUs":"$15.95","dimensions":"18.8 x 4.8 x 4.6 cm, 0.25 kg","expiryDate":"undefined undefined","rating":"16"},{"firstImage":"https://cloudinary.images-iherb.com/image/upload/f_auto,q_auto:eco/images/wsh/wsh95392/u/11.jpg","popularity":4,"productUrl":"https://www.iherb.com/pr/9wishes-rice-radiance-cream-1-7-fl-oz-50-ml/116992","title":"9Wishes, Rice Radiance Cream, 1.7 fl oz (50 ml)","weight":"0.21 kg","quantity":"50.27 ml","priceUs":"$19.10","dimensions":"6.7 x 6.6 x 5.8 cm, 0.21 kg","expiryDate":"undefined undefined","rating":"18"},{"firstImage":"https://cloudinary.images-iherb.com/image/upload/f_auto,q_auto:eco/images/wsh/wsh95150/u/9.jpg","popularity":5,"productUrl":"https://www.iherb.com/pr/9wishes-white-lucent-serum-1-7-fl-oz-50-ml/116989","title":"9Wishes, White Lucent Serum, 1.7 fl oz (50  ml)","weight":"0.12 kg","quantity":"50.27 ml","priceUs":"$16.80","dimensions":"12.3 x 3.9 x 3.9 cm, 0.12 kg","expiryDate":"undefined undefined","rating":"13"},{"firstImage":"https://cloudinary.images-iherb.com/image/upload/f_auto,q_auto:eco/images/dzc/dzc03047/u/2.jpg","popularity":6,"productUrl":"https://www.iherb.com/pr/9wishes-pine-ampule-serum-0-85-fl-oz-25-ml/114671","title":"9Wishes, Pine, Ampule Serum, 0.85 fl oz (25 ml)","weight":"0.09 kg","quantity":"25.14 ml","priceUs":"$21.60","dimensions":"10.9 x 3.7 x 3.4 cm, 0.09 kg","expiryDate":"undefined undefined","rating":"255"},{"firstImage":"https://cloudinary.images-iherb.com/image/upload/f_auto,q_auto:eco/images/dzc/dzc03024/u/2.jpg","popularity":7,"productUrl":"https://www.iherb.com/pr/9wishes-ampule-serum-calm-0-85-fl-oz-25-ml/90319","title":"9Wishes, Ampule Serum, Calm, 0.85 fl oz (25 ml)","weight":"0.09 kg","quantity":"25.14 ml","priceUs":"$12.00","dimensions":"10.9 x 3.7 x 3.6 cm, 0.09 kg","expiryDate":"undefined undefined","rating":"41"},{"firstImage":"https://cloudinary.images-iherb.com/image/upload/f_auto,q_auto:eco/images/dzc/dzc03049/u/2.jpg","popularity":8,"productUrl":"https://www.iherb.com/pr/9wishes-propolis-extract-81-1-fl-oz-30-ml/116991","title":"9Wishes, Propolis Extract 81%, 1 fl oz (30 ml)","weight":"0.14 kg","quantity":"29.57 ml","priceUs":"$20.30","dimensions":"10.7 x 4.7 x 4.7 cm, 0.14 kg","expiryDate":"undefined undefined","rating":"8"},{"firstImage":"https://cloudinary.images-iherb.com/image/upload/f_auto,q_auto:eco/images/dzc/dzc03048/u/2.jpg","popularity":9,"productUrl":"https://www.iherb.com/pr/a-dozen-cousins-jamaican-jerk-seasoning-medium-3-oz-85-g/116411","title":"A Dozen Cousins, Jamaican Jerk Seasoning, Medium, 3 oz (85 g)","weight":"0.09 kg","quantity":"85.05 g","priceUs":"$3.61","dimensions":"12.3 x 6.6 x 3.2 cm, 0.09 kg","expiryDate":"undefined undefined","rating":"34"},{"firstImage":"https://cloudinary.images-iherb.com/image/upload/f_auto,q_auto:eco/images/dzc/dzc03002/u/2.jpg","popularity":10,"productUrl":"https://www.iherb.com/pr/a-dozen-cousins-caribbean-coconut-rice-seasoning-sauce-4-oz-113/116398","title":"A Dozen Cousins, Caribbean Coconut Rice, Seasoning Sauce, 4 oz (113)","weight":"0.13 kg","quantity":"113.4 g","priceUs":"$3.61","dimensions":"12.4 x 7.2 x 5.5 cm, 0.12 kg","expiryDate":"undefined undefined","rating":"23"},{"firstImage":"https://cloudinary.images-iherb.com/image/upload/f_auto,q_auto:eco/images/amp/amp00031/u/13.jpg","popularity":11,"productUrl":"https://www.iherb.com/pr/a-dozen-cousins-peruvian-pollo-a-la-brasa-seasoning-sauce-mild-3-oz-85-g/116414","title":"A Dozen Cousins, Peruvian Pollo A La Brasa, Seasoning Sauce, Mild, 3 oz (85 g)","weight":"0.1 kg","quantity":"85.05 g","priceUs":"$3.61","dimensions":"12.6 x 7.2 x 2.9 cm, 0.1 kg","expiryDate":"undefined undefined","rating":"29"},{"firstImage":"https://cloudinary.images-iherb.com/image/upload/f_auto,q_auto:eco/images/amp/amp00030/u/23.jpg","popularity":12,"productUrl":"https://www.iherb.com/pr/a-dozen-cousins-mexican-pollo-asado-seasoning-sauce-3-oz-85-g/116415","title":"A Dozen Cousins, Mexican Pollo Asado Seasoning Sauce, 3 oz (85 g)","weight":"0.09 kg","quantity":"85.05 g","priceUs":"$3.61","dimensions":"12.6 x 7.1 x 2.9 cm, 0.09 kg","expiryDate":"undefined undefined","rating":"48"},{"firstImage":"https://cloudinary.images-iherb.com/image/upload/f_auto,q_auto:eco/images/amp/amp01145/u/7.jpg","popularity":13,"productUrl":"https://www.iherb.com/pr/a-dozen-cousins-trini-chickpea-curry-mild-10-oz-283-g/116399","title":"A Dozen Cousins, Trini Chickpea Curry, Mild, 10 oz (283 g)","weight":"0.29 kg","quantity":"283.5 g","priceUs":"$4.51","dimensions":"13.6 x 9.8 x 6.9 cm, 0.29 kg","expiryDate":"undefined undefined","rating":"9"},{"firstImage":"https://cloudinary.images-iherb.com/image/upload/f_auto,q_auto:eco/images/amp/amp01244/u/23.jpg","popularity":14,"productUrl":"https://www.iherb.com/pr/a-la-maison-de-provence-liquid-soap-for-hand-body-rosemary-mint-16-9-fl-oz-500-ml/52707","title":"A La Maison de Provence, Liquid Soap For Hand &amp; Body, Rosemary Mint, 16.9 fl oz (500 ml)","weight":"0.54 kg","quantity":"499.79 ml","priceUs":"$7.59","dimensions":"5.8 x 8.6 x 18.5 cm, 0.54 kg","expiryDate":"January 2027","rating":"4,813"},{"firstImage":"https://cloudinary.images-iherb.com/image/upload/f_auto,q_auto:eco/images/amp/amp01008/u/28.jpg","popularity":15,"productUrl":"https://www.iherb.com/pr/a-la-maison-de-provence-liquid-soap-for-hand-body-white-tea-16-9-fl-oz-500-ml/55958","title":"A La Maison de Provence, Liquid Soap for Hand &amp; Body, White Tea, 16.9 fl oz (500 ml)","weight":"499.79 ml","quantity":"\n                            <span class=\"product-weight\">\n                                    <span class=\"toggle-weight-preference\" name=\"wpc\" data-current-wpc=\"2\" data-imperial=\"2.3 x 3.4 x 7.3 in, 1.2 lb\" data-metric=\"5.8 x 8.6 x 18.5 cm, 0.54 kg\">5.8 x 8.6 x 18.5 cm, 0.54 kg</span>\n                            </span>\n                        ","priceUs":"$7.59","dimensions":"11.6 x 8.3 x 5 cm, 0.41 kg","expiryDate":"undefined undefined","rating":"1,464"},{"firstImage":"https://cloudinary.images-iherb.com/image/upload/f_auto,q_auto:eco/images/amp/amp01010/u/16.jpg","popularity":16,"productUrl":"https://www.iherb.com/pr/a-la-maison-de-provence-liquid-soap-for-hand-body-rose-lilac-16-9-fl-oz-500-ml/68504","title":"A La Maison de Provence, Liquid Soap For Hand &amp; Body, Rose Lilac, 16.9 fl oz (500 ml)","weight":"499.79 ml","quantity":"\n                            <span class=\"product-weight\">\n                                    <span class=\"toggle-weight-preference\" name=\"wpc\" data-current-wpc=\"2\" data-imperial=\"2.3 x 3.4 x 7.3 in, 1.2 lb\" data-metric=\"5.8 x 8.6 x 18.5 cm, 0.54 kg\">5.8 x 8.6 x 18.5 cm, 0.54 kg</span>\n                            </span>\n                        ","priceUs":"$7.59","dimensions":"5.8 x 8.6 x 18.5 cm, 0.54 kg","expiryDate":"undefined undefined","rating":"1,382"},{"popularity":17,"productUrl":"https://www.iherb.com/pr/a-la-maison-de-provence-liquid-soap-for-hand-body-citrus-blossom-16-9-fl-oz-500-ml/80284","title":"A La Maison de Provence, Liquid Soap For Hand &amp; Body, Citrus Blossom, 16.9 fl oz (500 ml)","weight":"499.79 ml","quantity":"\n                            <span class=\"product-weight\">\n                                    <span class=\"toggle-weight-preference\" name=\"wpc\" data-current-wpc=\"2\" data-imperial=\"2.3 x 3.4 x 7.3 in, 1.2 lb\" data-metric=\"5.8 x 8.6 x 18.5 cm, 0.54 kg\">5.8 x 8.6 x 18.5 cm, 0.54 kg</span>\n                            </span>\n                        ","priceUs":"$7.59","dimensions":"5.8 x 8.6 x 18.5 cm, 0.54 kg","expiryDate":"undefined undefined","rating":"1,209"},{"popularity":18,"productUrl":"https://www.iherb.com/pr/a-la-maison-de-provence-hand-body-bar-soap-oat-milk-4-bars-3-5-oz-100-g-each/55985","title":"A La Maison de Provence, Hand &amp; Body Bar Soap, Oat Milk, 4 Bars, 3.5 oz (100 g) Each","weight":"0.41 kg","quantity":"4 Count","priceUs":"$7.00","expiryDate":"January 2027","rating":"1,006"},{"popularity":19,"productUrl":"https://www.iherb.com/pr/a-la-maison-de-provence-hand-body-bar-soap-lavender-flowers-4-bars-3-5-oz-100-g-each/55984","title":"A La Maison de Provence, Hand &amp; Body Bar Soap, Lavender Flowers, 4 Bars, 3.5 oz (100 g) Each","weight":"4 Count","quantity":"\n                            <span class=\"product-weight\">\n                                    <span class=\"toggle-weight-preference\" name=\"wpc\" data-current-wpc=\"2\" data-imperial=\"4.3 x 2 x 3.2 in, 0.9 lb\" data-metric=\"10.9 x 5.1 x 8.1 cm, 0.41 kg\">10.9 x 5.1 x 8.1 cm, 0.41 kg</span>\n                            </span>\n                        ","priceUs":"$6.99","expiryDate":"undefined undefined","rating":"1,980"},{"popularity":20,"productUrl":"https://www.iherb.com/pr/a-la-maison-de-provence-hand-body-bar-soap-fresh-sea-salt-4-bars-3-5-oz-100-g-each/65299","title":"A La Maison de Provence, Hand &amp; Body Bar Soap, Fresh Sea Salt, 4 Bars, 3.5 oz (100 g) Each","weight":"4 Count","quantity":"\n                            <span class=\"product-weight\">\n                                    <span class=\"toggle-weight-preference\" name=\"wpc\" data-current-wpc=\"2\" data-imperial=\"4 x 2 x 3 in, 0.9 lb\" data-metric=\"10.2 x 5.1 x 7.6 cm, 0.41 kg\">10.2 x 5.1 x 7.6 cm, 0.41 kg</span>\n                            </span>\n                        ","priceUs":"$7.00","expiryDate":"undefined undefined","rating":"1,199"},{"popularity":21,"productUrl":"https://www.iherb.com/pr/a-la-maison-de-provence-liquid-soap-for-hand-body-heirloom-peach-16-9-fl-oz-500-ml/111732","title":"A La Maison de Provence, Liquid Soap For Hand &amp; Body, Heirloom Peach, 16.9 fl oz (500 ml)","weight":"499.79 ml","quantity":"\n                            <span class=\"product-weight\">\n                                    <span class=\"toggle-weight-preference\" name=\"wpc\" data-current-wpc=\"2\" data-imperial=\"2.3 x 3.4 x 7.3 in, 1.2 lb\" data-metric=\"5.8 x 8.6 x 18.5 cm, 0.54 kg\">5.8 x 8.6 x 18.5 cm, 0.54 kg</span>\n                            </span>\n                        ","priceUs":"$7.59","expiryDate":"undefined undefined","rating":"437"},{"popularity":22,"productUrl":"https://www.iherb.com/pr/a-la-maison-de-provence-hand-body-bar-soap-pure-coconut-4-bars-3-5-oz-100-g-each/65298","title":"A La Maison de Provence, Hand &amp; Body Bar Soap, Pure Coconut, 4 Bars, 3.5 oz (100 g) Each","weight":"4 Count","quantity":"\n                            <span class=\"product-weight\">\n                                    <span class=\"toggle-weight-preference\" name=\"wpc\" data-current-wpc=\"2\" data-imperial=\"4 x 2 x 3 in, 0.9 lb\" data-metric=\"10.2 x 5.1 x 7.6 cm, 0.41 kg\">10.2 x 5.1 x 7.6 cm, 0.41 kg</span>\n                            </span>\n                        ","priceUs":"$6.99","expiryDate":"undefined undefined","rating":"730"},{"popularity":23,"productUrl":"https://www.iherb.com/pr/a-la-maison-de-provence-liquid-soap-for-hand-body-plumeria-16-9-fl-oz-500-ml/111734","title":"A La Maison de Provence, Liquid Soap For Hand &amp; Body, Plumeria, 16.9 fl oz (500 ml)","weight":"499.79 ml","quantity":"\n                            <span class=\"product-weight\">\n                                    <span class=\"toggle-weight-preference\" name=\"wpc\" data-current-wpc=\"2\" data-imperial=\"2.3 x 3.4 x 7.3 in, 1.2 lb\" data-metric=\"5.8 x 8.6 x 18.5 cm, 0.54 kg\">5.8 x 8.6 x 18.5 cm, 0.54 kg</span>\n                            </span>\n                        ","priceUs":"$7.59","expiryDate":"undefined undefined","rating":"750"},{"popularity":24,"productUrl":"https://www.iherb.com/pr/a-la-maison-de-provence-liquid-soap-for-hand-body-yuzu-lime-16-9-fl-oz-500-ml/56455","title":"A La Maison de Provence, Liquid Soap For Hand &amp; Body, Yuzu Lime, 16.9 fl oz (500 ml)","weight":"499.79 ml","quantity":"\n                            <span class=\"product-weight\">\n                                    <span class=\"toggle-weight-preference\" name=\"wpc\" data-current-wpc=\"2\" data-imperial=\"2.3 x 3.4 x 7.3 in, 1.2 lb\" data-metric=\"5.8 x 8.6 x 18.5 cm, 0.54 kg\">5.8 x 8.6 x 18.5 cm, 0.54 kg</span>\n                            </span>\n                        ","priceUs":"$7.59","expiryDate":"undefined undefined","rating":"850"},{"popularity":25,"productUrl":"https://www.iherb.com/pr/a-la-maison-de-provence-liquid-soap-for-hands-body-provence-lemon-16-9-fl-oz-500-ml/100194","title":"A La Maison de Provence, Liquid Soap For Hands &amp; Body, Provence Lemon, 16.9 fl oz (500 ml)","weight":"499.79 ml","quantity":"\n                            <span class=\"product-weight\">\n                                    <span class=\"toggle-weight-preference\" name=\"wpc\" data-current-wpc=\"2\" data-imperial=\"7.2 x 3.45 x 2.3 in, 1.25 lb\" data-metric=\"18.3 x 8.8 x 5.8 cm, 0.57 kg\">18.3 x 8.8 x 5.8 cm, 0.57 kg</span>\n                            </span>\n                        ","priceUs":"$7.59","expiryDate":"undefined undefined","rating":"499"},{"popularity":26,"productUrl":"https://www.iherb.com/pr/a-la-maison-de-provence-liquid-soap-for-hand-body-lavender-aloe-16-9-fl-oz-500-ml/52706","title":"A La Maison de Provence, Liquid Soap For Hand &amp; Body, Lavender Aloe, 16.9 fl oz (500 ml)","weight":"499.79 ml","quantity":"\n                            <span class=\"product-weight\">\n                                    <span class=\"toggle-weight-preference\" name=\"wpc\" data-current-wpc=\"2\" data-imperial=\"2.3 x 3.4 x 7.3 in, 1.2 lb\" data-metric=\"5.8 x 8.6 x 18.5 cm, 0.54 kg\">5.8 x 8.6 x 18.5 cm, 0.54 kg</span>\n                            </span>\n                        ","priceUs":"$7.59","expiryDate":"undefined undefined","rating":"1,098"},{"popularity":27,"productUrl":"https://www.iherb.com/pr/a-la-maison-de-provence-liquid-soap-for-hand-body-honeysuckle-16-9-fl-oz-500-ml/52709","title":"A La Maison de Provence, Liquid Soap For Hand &amp; Body, Honeysuckle, 16.9 fl oz (500 ml)","weight":"499.79 ml","quantity":"\n                            <span class=\"product-weight\">\n                                    <span class=\"toggle-weight-preference\" name=\"wpc\" data-current-wpc=\"2\" data-imperial=\"2.3 x 3.4 x 7.3 in, 1.2 lb\" data-metric=\"5.8 x 8.6 x 18.5 cm, 0.54 kg\">5.8 x 8.6 x 18.5 cm, 0.54 kg</span>\n                            </span>\n                        ","priceUs":"$7.59","expiryDate":"undefined undefined","rating":"882"},{"popularity":28,"productUrl":"https://www.iherb.com/pr/a-la-maison-de-provence-liquid-soap-for-hand-body-cherry-blossom-16-9-fl-oz-500-ml/85232","title":"A La Maison de Provence, Liquid Soap For Hand &amp; Body, Cherry Blossom, 16.9 fl oz (500 ml)","weight":"0.54 kg","quantity":"499.79 ml","priceUs":"$7.59","expiryDate":"January 2027","rating":"1,323"},{"popularity":29,"productUrl":"https://www.iherb.com/pr/a-la-maison-de-provence-hand-body-bar-soap-sweet-almond-4-bars-3-5-oz-100-g-each/65300","title":"A La Maison de Provence, Hand &amp; Body Bar Soap, Sweet Almond, 4 Bars, 3.5 oz (100 g) Each","weight":"4 Count","quantity":"\n                            <span class=\"product-weight\">\n                                    <span class=\"toggle-weight-preference\" name=\"wpc\" data-current-wpc=\"2\" data-imperial=\"4 x 2 x 3 in, 0.9 lb\" data-metric=\"10.2 x 5.1 x 7.6 cm, 0.41 kg\">10.2 x 5.1 x 7.6 cm, 0.41 kg</span>\n                            </span>\n                        ","priceUs":"$6.99","expiryDate":"undefined undefined","rating":"1,140"},{"popularity":30,"productUrl":"https://www.iherb.com/pr/a-la-maison-de-provence-hand-body-bar-soap-rosemary-mint-4-bars-3-5-oz-100-g-each/55986","title":"A La Maison de Provence, Hand &amp; Body Bar Soap, Rosemary Mint, 4 Bars, 3.5 oz (100 g) Each","weight":"4 Count","quantity":"\n                            <span class=\"product-weight\">\n                                    <span class=\"toggle-weight-preference\" name=\"wpc\" data-current-wpc=\"2\" data-imperial=\"4.3 x 2 x 3.2 in, 0.9 lb\" data-metric=\"10.9 x 5.1 x 8.1 cm, 0.41 kg\">10.9 x 5.1 x 8.1 cm, 0.41 kg</span>\n                            </span>\n                        ","priceUs":"$6.99","expiryDate":"undefined undefined","rating":"1,449"},{"popularity":31,"productUrl":"https://www.iherb.com/pr/a-la-maison-de-provence-liquid-soap-for-hand-body-pure-coconut-16-9-fl-oz-500-ml/55972","title":"A La Maison de Provence, Liquid Soap For Hand &amp; Body, Pure Coconut, 16.9 fl oz (500 ml)","weight":"499.79 ml","quantity":"\n                            <span class=\"product-weight\">\n                                    <span class=\"toggle-weight-preference\" name=\"wpc\" data-current-wpc=\"2\" data-imperial=\"2.3 x 3.4 x 7.3 in, 1.2 lb\" data-metric=\"5.8 x 8.6 x 18.5 cm, 0.54 kg\">5.8 x 8.6 x 18.5 cm, 0.54 kg</span>\n                            </span>\n                        ","priceUs":"$7.59","expiryDate":"undefined undefined","rating":"456"},{"popularity":32,"productUrl":"https://www.iherb.com/pr/a-la-maison-de-provence-liquid-soap-for-hand-body-sweet-almond-16-9-fl-oz-500-ml/63838","title":"A La Maison de Provence, Liquid Soap For Hand &amp; Body, Sweet Almond, 16.9 fl oz (500 ml)","weight":"0.54 kg","quantity":"499.79 ml","priceUs":"$7.59","expiryDate":"January 2027","rating":"723"}]