[{"firstImage":"https://cloudinary.images-iherb.com/image/upload/f_auto,q_auto:eco/images/hpr/hpr87031/u/14.jpg","popularity":0,"productUrl":"https://www.iherb.com/pr/alr-industries-humapro-1-087-mg-450-coated-tablets-217-mg-per-tablet/73544","title":"ALR Industries, HumaPro, 1,087 mg, 450 Coated Tablets (217 mg per Tablet)","weight":"0.82 kg","quantity":"450 Count","priceUs":"$50.94","dimensions":"17.1 x 9.4 x 9.3 cm, 0.82 kg","expiryDate":"January 2026","rating":"1"},{"firstImage":"https://cloudinary.images-iherb.com/image/upload/f_auto,q_auto:eco/images/hpr/hpr36726/u/15.jpg","popularity":1,"productUrl":"https://www.iherb.com/pr/alr-industries-humapro-strawberry-kiwi-23-52-oz-667-g/73542","title":"ALR Industries, HumaPro, Strawberry-Kiwi, 23.52 oz (667 g)","weight":"0.79 kg","quantity":"666.78 g","priceUs":"$53.61","dimensions":"17.7 x 12.7 x 12.7 cm, 0.79 kg","expiryDate":"February 2027"},{"firstImage":"https://cloudinary.images-iherb.com/image/upload/f_auto,q_auto:eco/images/hpr/hpr87034/u/11.jpg","popularity":2,"productUrl":"https://www.iherb.com/pr/alr-industries-humapro-sour-grape-23-52-oz-667-g/131627","title":"ALR Industries, Hyperdrive 4.0, 660 mg, 60 Capsules","weight":"0.07 kg","quantity":"60 Count","priceUs":"$32.15","dimensions":"10.5 x 5 x 5 cm, 0.07 kg","expiryDate":"March 2025"},{"firstImage":"https://cloudinary.images-iherb.com/image/upload/f_auto,q_auto:eco/images/hpr/hpr39365/u/8.jpg","popularity":3,"productUrl":"https://www.iherb.com/pr/alr-industries-hyperdrive-4-0-660-mg-60-capsules/130117","title":"ALR Industries, HumaPro, Sour Grape, 23.52 oz (667 g)","weight":"0.82 kg","quantity":"666.78 g","priceUs":"$53.61","dimensions":"18.3 x 17.7 x 12.7 cm, 0.82 kg","expiryDate":"January 2026"},{"firstImage":"https://cloudinary.images-iherb.com/image/upload/f_auto,q_auto:eco/images/hpr/hpr02274/u/10.jpg","popularity":4,"productUrl":"https://www.iherb.com/pr/alr-industries-humapro-southern-sweet-tea-23-52-oz-667-g/130115","title":"ALR Industries, HumaPro, Southern Sweet Tea, 23.52 oz (667 g)","weight":"0.79 kg","quantity":"666.78 g","priceUs":"$53.61","dimensions":"17.7 x 12.6 x 12.6 cm, 0.79 kg","expiryDate":"May 2027"},{"firstImage":"https://cloudinary.images-iherb.com/image/upload/f_auto,q_auto:eco/images/hpr/hpr02388/u/10.jpg","popularity":5,"productUrl":"https://www.iherb.com/pr/alr-industries-humapro-passion-fruit-23-52-oz-667-g/131626","title":"ALR Industries, HumaPro, Passion Fruit, 23.52 oz (667 g)","weight":"0.79 kg","quantity":"666.78 g","priceUs":"$53.61","dimensions":"17.7 x 12.7 x 12.6 cm, 0.79 kg","expiryDate":"May 2026"},{"popularity":6,"productUrl":"https://www.iherb.com/pr/alr-industries-humapro-blue-raspberry-23-52-oz-667-g/130113","title":"ALR Industries, HumaPro, Blue Raspberry, 23.52 oz (667 g)","weight":"0.79 kg","quantity":"666.78 g","priceUs":"$53.61","dimensions":"17.7 x 12.6 x 12.6 cm, 0.79 kg","expiryDate":"June 2027"},{"popularity":7,"productUrl":"https://www.iherb.com/pr/alr-industries-humapro-rocket-pop-23-52-oz-667-g/130114","title":"ALR Industries, HumaPro, Rocket Pop, 23.52 oz (667 g)","weight":"0.82 kg","quantity":"666.78 g","priceUs":"$53.61","dimensions":"17.7 x 12.7 x 12.6 cm, 0.82 kg","expiryDate":"January 2027"},{"popularity":8,"productUrl":"https://www.iherb.com/pr/alr-industries-chain-d-out-berry-banana-10-58-oz-300-g/130110","title":"ALR Industries, Chain'd Out, Berry Banana, 10.58 oz (300 g)","weight":"299.94 g","quantity":"\n                            <span class=\"product-weight\">\n                                    <span class=\"toggle-weight-preference\" name=\"wpc\" data-current-wpc=\"2\" data-imperial=\"6.15 x 3.7 x 3.7 in, 0.85 lb\" data-metric=\"15.6 x 9.4 x 9.4 cm, 0.39 kg\">15.6 x 9.4 x 9.4 cm, 0.39 kg</span>\n                            </span>\n                        ","priceUs":"$27.95","expiryDate":"undefined undefined"},{"popularity":9,"productUrl":"https://www.iherb.com/pr/alr-industries-chain-d-out-blue-raspberry-10-58-oz-300-g/130111","title":"ALR Industries, Chain'D Out, Blue Raspberry, 10.58 oz (300 g)","weight":"299.94 g","quantity":"\n                            <span class=\"product-weight\">\n                                    <span class=\"toggle-weight-preference\" name=\"wpc\" data-current-wpc=\"2\" data-imperial=\"6.15 x 3.7 x 3.7 in, 0.85 lb\" data-metric=\"15.6 x 9.4 x 9.4 cm, 0.39 kg\">15.6 x 9.4 x 9.4 cm, 0.39 kg</span>\n                            </span>\n                        ","priceUs":"$27.95","expiryDate":"undefined undefined"},{"popularity":10,"productUrl":"https://www.iherb.com/pr/alr-industries-chain-d-out-lemon-lime-10-58-oz-300-g/130112","title":"ALR Industries, Chain'd Out, Lemon-Lime , 10.58 oz (300 g)","weight":"299.94 g","quantity":"\n                            <span class=\"product-weight\">\n                                    <span class=\"toggle-weight-preference\" name=\"wpc\" data-current-wpc=\"2\" data-imperial=\"6.15 x 3.7 x 3.7 in, 0.85 lb\" data-metric=\"15.6 x 9.4 x 9.4 cm, 0.39 kg\">15.6 x 9.4 x 9.4 cm, 0.39 kg</span>\n                            </span>\n                        ","priceUs":"$27.95","expiryDate":"undefined undefined"},{"firstImage":"https://cloudinary.images-iherb.com/image/upload/f_auto,q_auto:eco/images/hpr/hpr87031/u/14.jpg","popularity":0,"productUrl":"https://www.iherb.com/pr/alr-industries-humapro-1-087-mg-450-coated-tablets-217-mg-per-tablet/73544","title":"ALR Industries, HumaPro, 1,087 mg, 450 Coated Tablets (217 mg per Tablet)","weight":"0.82 kg","quantity":"450 Count","priceUs":"$50.94","dimensions":"17.1 x 9.4 x 9.3 cm, 0.82 kg","expiryDate":"undefined undefined","rating":"1"},{"firstImage":"https://cloudinary.images-iherb.com/image/upload/f_auto,q_auto:eco/images/hpr/hpr36726/u/15.jpg","popularity":1,"productUrl":"https://www.iherb.com/pr/alr-industries-humapro-strawberry-kiwi-23-52-oz-667-g/73542","title":"ALR Industries, HumaPro, Strawberry-Kiwi, 23.52 oz (667 g)","weight":"0.79 kg","quantity":"666.78 g","priceUs":"$53.61","dimensions":"17.7 x 12.7 x 12.7 cm, 0.79 kg","expiryDate":"undefined undefined","rating":"989"},{"firstImage":"https://cloudinary.images-iherb.com/image/upload/f_auto,q_auto:eco/images/hpr/hpr87034/u/11.jpg","popularity":2,"productUrl":"https://www.iherb.com/pr/alr-industries-humapro-sour-grape-23-52-oz-667-g/131627","title":"ALR Industries, Hyperdrive 4.0, 660 mg, 60 Capsules","weight":"0.07 kg","quantity":"60 Count","priceUs":"$32.15","dimensions":"10.5 x 5 x 5 cm, 0.07 kg","expiryDate":"undefined undefined","rating":"650"},{"firstImage":"https://cloudinary.images-iherb.com/image/upload/f_auto,q_auto:eco/images/hpr/hpr39365/u/8.jpg","popularity":3,"productUrl":"https://www.iherb.com/pr/alr-industries-hyperdrive-4-0-660-mg-60-capsules/130117","title":"ALR Industries, HumaPro, Sour Grape, 23.52 oz (667 g)","weight":"0.82 kg","quantity":"666.78 g","priceUs":"$53.61","dimensions":"18.3 x 17.7 x 12.7 cm, 0.82 kg","expiryDate":"undefined undefined","rating":"5"},{"firstImage":"https://cloudinary.images-iherb.com/image/upload/f_auto,q_auto:eco/images/hpr/hpr02274/u/10.jpg","popularity":4,"productUrl":"https://www.iherb.com/pr/alr-industries-humapro-southern-sweet-tea-23-52-oz-667-g/130115","title":"ALR Industries, HumaPro, Southern Sweet Tea, 23.52 oz (667 g)","weight":"0.79 kg","quantity":"666.78 g","priceUs":"$53.61","dimensions":"17.7 x 12.6 x 12.6 cm, 0.79 kg","expiryDate":"undefined undefined","rating":"2"},{"firstImage":"https://cloudinary.images-iherb.com/image/upload/f_auto,q_auto:eco/images/hpr/hpr02388/u/10.jpg","popularity":5,"productUrl":"https://www.iherb.com/pr/alr-industries-humapro-passion-fruit-23-52-oz-667-g/131626","title":"ALR Industries, HumaPro, Passion Fruit, 23.52 oz (667 g)","weight":"0.79 kg","quantity":"666.78 g","priceUs":"$53.61","dimensions":"17.7 x 12.7 x 12.6 cm, 0.79 kg","expiryDate":"undefined undefined","rating":"1"},{"firstImage":"https://cloudinary.images-iherb.com/image/upload/f_auto,q_auto:eco/images/ahp/ahp00060/u/29.jpg","popularity":6,"productUrl":"https://www.iherb.com/pr/alr-industries-humapro-blue-raspberry-23-52-oz-667-g/130113","title":"ALR Industries, HumaPro, Blue Raspberry, 23.52 oz (667 g)","weight":"0.79 kg","quantity":"666.78 g","priceUs":"$53.61","dimensions":"17.7 x 12.6 x 12.6 cm, 0.79 kg","expiryDate":"undefined undefined"},{"firstImage":"https://cloudinary.images-iherb.com/image/upload/f_auto,q_auto:eco/images/ahp/ahp00022/u/32.jpg","popularity":7,"productUrl":"https://www.iherb.com/pr/alr-industries-humapro-rocket-pop-23-52-oz-667-g/130114","title":"ALR Industries, HumaPro, Rocket Pop, 23.52 oz (667 g)","weight":"0.82 kg","quantity":"666.78 g","priceUs":"$53.61","dimensions":"17.7 x 12.7 x 12.6 cm, 0.82 kg","expiryDate":"undefined undefined"},{"firstImage":"https://cloudinary.images-iherb.com/image/upload/f_auto,q_auto:eco/images/ahp/ahp00050/u/13.jpg","popularity":8,"productUrl":"https://www.iherb.com/pr/alr-industries-chain-d-out-berry-banana-10-58-oz-300-g/130110","title":"ALR Industries, Chain'd Out, Berry Banana, 10.58 oz (300 g)","weight":"299.94 g","quantity":"\n                            <span class=\"product-weight\">\n                                    <span class=\"toggle-weight-preference\" name=\"wpc\" data-current-wpc=\"2\" data-imperial=\"6.15 x 3.7 x 3.7 in, 0.85 lb\" data-metric=\"15.6 x 9.4 x 9.4 cm, 0.39 kg\">15.6 x 9.4 x 9.4 cm, 0.39 kg</span>\n                            </span>\n                        ","priceUs":"$27.95","dimensions":"9.9 x 5.3 x 5.3 cm, 0.11 kg","expiryDate":"undefined undefined"},{"firstImage":"https://cloudinary.images-iherb.com/image/upload/f_auto,q_auto:eco/images/ahp/ahp00034/u/13.jpg","popularity":9,"productUrl":"https://www.iherb.com/pr/alr-industries-chain-d-out-blue-raspberry-10-58-oz-300-g/130111","title":"ALR Industries, Chain'D Out, Blue Raspberry, 10.58 oz (300 g)","weight":"299.94 g","quantity":"\n                            <span class=\"product-weight\">\n                                    <span class=\"toggle-weight-preference\" name=\"wpc\" data-current-wpc=\"2\" data-imperial=\"6.15 x 3.7 x 3.7 in, 0.85 lb\" data-metric=\"15.6 x 9.4 x 9.4 cm, 0.39 kg\">15.6 x 9.4 x 9.4 cm, 0.39 kg</span>\n                            </span>\n                        ","priceUs":"$27.95","dimensions":"5.3 x 5.3 x 9.4 cm, 0.14 kg","expiryDate":"undefined undefined"},{"firstImage":"https://cloudinary.images-iherb.com/image/upload/f_auto,q_auto:eco/images/ahp/ahp00030/u/13.jpg","popularity":10,"productUrl":"https://www.iherb.com/pr/alr-industries-chain-d-out-lemon-lime-10-58-oz-300-g/130112","title":"ALR Industries, Chain'd Out, Lemon-Lime , 10.58 oz (300 g)","weight":"299.94 g","quantity":"\n                            <span class=\"product-weight\">\n                                    <span class=\"toggle-weight-preference\" name=\"wpc\" data-current-wpc=\"2\" data-imperial=\"6.15 x 3.7 x 3.7 in, 0.85 lb\" data-metric=\"15.6 x 9.4 x 9.4 cm, 0.39 kg\">15.6 x 9.4 x 9.4 cm, 0.39 kg</span>\n                            </span>\n                        ","priceUs":"$27.95","dimensions":"18.7 x 9.8 x 5.3 cm, 0.09 kg","expiryDate":"undefined undefined"},{"popularity":11,"productUrl":"https://www.iherb.com/pr/alta-health-magnesium-chloride-100-tablets/10682","title":"Alta Health, Magnesium Chloride, 100 Tablets","weight":"0.11 kg","quantity":"100 Count","priceUs":"$15.17","dimensions":"8.9 x 8.5 x 7.2 cm, 0.16 kg","expiryDate":"July 2025"},{"popularity":12,"productUrl":"https://www.iherb.com/pr/alta-health-herbal-silica-with-bioflavonoids-120-tablets/5683","title":"Alta Health, Herbal Silica with Bioflavonoids, 120 Tablets","weight":"0.14 kg","quantity":"120 Count","priceUs":"$24.48","dimensions":"9.7 x 7.1 x 5.2 cm, 0.09 kg","expiryDate":"June 2025"},{"popularity":13,"productUrl":"https://www.iherb.com/pr/alta-health-potassium-chloride-plus-silica-100-capsules/9134","title":"Alta Health, Potassium Chloride, Plus Silica, 100 Capsules","weight":"0.19 kg","quantity":"100 Count","priceUs":"$16.14","expiryDate":"July 2025"},{"popularity":14,"productUrl":"https://www.iherb.com/pr/alta-health-can-gest-a-natural-digestive-aid-4-oz/12389","title":"Alta Health, Can-Gest, A Natural Digestive Aid, 4 oz","weight":"0.16 kg","quantity":"113.4 g","priceUs":"$22.02","expiryDate":"October 2024"},{"popularity":15,"productUrl":"https://www.iherb.com/pr/alta-health-can-gest-natural-digestive-aid-100-capsules/13009","title":"Alta Health, Can-Gest, Natural Digestive Aid, 100 Capsules","weight":"0.09 kg","quantity":"100 Count","priceUs":"$19.09","expiryDate":"May 2025"},{"firstImage":"https://cloudinary.images-iherb.com/image/upload/f_auto,q_auto:eco/images/hpr/hpr87031/u/14.jpg","popularity":0,"productUrl":"https://www.iherb.com/pr/alr-industries-humapro-1-087-mg-450-coated-tablets-217-mg-per-tablet/73544","title":"ALR Industries, HumaPro, 1,087 mg, 450 Coated Tablets (217 mg per Tablet)","weight":"0.82 kg","quantity":"450 Count","priceUs":"$50.94","dimensions":"17.1 x 9.4 x 9.3 cm, 0.82 kg","expiryDate":"undefined undefined","rating":"1"},{"firstImage":"https://cloudinary.images-iherb.com/image/upload/f_auto,q_auto:eco/images/hpr/hpr36726/u/15.jpg","popularity":1,"productUrl":"https://www.iherb.com/pr/alr-industries-humapro-strawberry-kiwi-23-52-oz-667-g/73542","title":"ALR Industries, HumaPro, Strawberry-Kiwi, 23.52 oz (667 g)","weight":"0.79 kg","quantity":"666.78 g","priceUs":"$53.61","dimensions":"17.7 x 12.7 x 12.7 cm, 0.79 kg","expiryDate":"undefined undefined","rating":"989"},{"firstImage":"https://cloudinary.images-iherb.com/image/upload/f_auto,q_auto:eco/images/hpr/hpr87034/u/11.jpg","popularity":2,"productUrl":"https://www.iherb.com/pr/alr-industries-humapro-sour-grape-23-52-oz-667-g/131627","title":"ALR Industries, Hyperdrive 4.0, 660 mg, 60 Capsules","weight":"0.07 kg","quantity":"60 Count","priceUs":"$32.15","dimensions":"10.5 x 5 x 5 cm, 0.07 kg","expiryDate":"undefined undefined","rating":"650"},{"firstImage":"https://cloudinary.images-iherb.com/image/upload/f_auto,q_auto:eco/images/hpr/hpr39365/u/8.jpg","popularity":3,"productUrl":"https://www.iherb.com/pr/alr-industries-hyperdrive-4-0-660-mg-60-capsules/130117","title":"ALR Industries, HumaPro, Sour Grape, 23.52 oz (667 g)","weight":"0.82 kg","quantity":"666.78 g","priceUs":"$53.61","dimensions":"18.3 x 17.7 x 12.7 cm, 0.82 kg","expiryDate":"undefined undefined","rating":"5"},{"firstImage":"https://cloudinary.images-iherb.com/image/upload/f_auto,q_auto:eco/images/hpr/hpr02274/u/10.jpg","popularity":4,"productUrl":"https://www.iherb.com/pr/alr-industries-humapro-southern-sweet-tea-23-52-oz-667-g/130115","title":"ALR Industries, HumaPro, Southern Sweet Tea, 23.52 oz (667 g)","weight":"0.79 kg","quantity":"666.78 g","priceUs":"$53.61","dimensions":"17.7 x 12.6 x 12.6 cm, 0.79 kg","expiryDate":"undefined undefined","rating":"2"},{"firstImage":"https://cloudinary.images-iherb.com/image/upload/f_auto,q_auto:eco/images/hpr/hpr02388/u/10.jpg","popularity":5,"productUrl":"https://www.iherb.com/pr/alr-industries-humapro-passion-fruit-23-52-oz-667-g/131626","title":"ALR Industries, HumaPro, Passion Fruit, 23.52 oz (667 g)","weight":"0.79 kg","quantity":"666.78 g","priceUs":"$53.61","dimensions":"17.7 x 12.7 x 12.6 cm, 0.79 kg","expiryDate":"undefined undefined","rating":"1"},{"firstImage":"https://cloudinary.images-iherb.com/image/upload/f_auto,q_auto:eco/images/ahp/ahp00060/u/29.jpg","popularity":6,"productUrl":"https://www.iherb.com/pr/alr-industries-humapro-blue-raspberry-23-52-oz-667-g/130113","title":"ALR Industries, HumaPro, Blue Raspberry, 23.52 oz (667 g)","weight":"0.79 kg","quantity":"666.78 g","priceUs":"$53.61","dimensions":"17.7 x 12.6 x 12.6 cm, 0.79 kg","expiryDate":"undefined undefined","rating":"1,841"},{"firstImage":"https://cloudinary.images-iherb.com/image/upload/f_auto,q_auto:eco/images/ahp/ahp00022/u/32.jpg","popularity":7,"productUrl":"https://www.iherb.com/pr/alr-industries-humapro-rocket-pop-23-52-oz-667-g/130114","title":"ALR Industries, HumaPro, Rocket Pop, 23.52 oz (667 g)","weight":"0.82 kg","quantity":"666.78 g","priceUs":"$53.61","dimensions":"17.7 x 12.7 x 12.6 cm, 0.82 kg","expiryDate":"undefined undefined","rating":"2,286"},{"firstImage":"https://cloudinary.images-iherb.com/image/upload/f_auto,q_auto:eco/images/ahp/ahp00050/u/13.jpg","popularity":8,"productUrl":"https://www.iherb.com/pr/alr-industries-chain-d-out-berry-banana-10-58-oz-300-g/130110","title":"ALR Industries, Chain'd Out, Berry Banana, 10.58 oz (300 g)","weight":"299.94 g","quantity":"\n                            <span class=\"product-weight\">\n                                    <span class=\"toggle-weight-preference\" name=\"wpc\" data-current-wpc=\"2\" data-imperial=\"6.15 x 3.7 x 3.7 in, 0.85 lb\" data-metric=\"15.6 x 9.4 x 9.4 cm, 0.39 kg\">15.6 x 9.4 x 9.4 cm, 0.39 kg</span>\n                            </span>\n                        ","priceUs":"$27.95","dimensions":"9.9 x 5.3 x 5.3 cm, 0.11 kg","expiryDate":"undefined undefined","rating":"1,138"},{"firstImage":"https://cloudinary.images-iherb.com/image/upload/f_auto,q_auto:eco/images/ahp/ahp00034/u/13.jpg","popularity":9,"productUrl":"https://www.iherb.com/pr/alr-industries-chain-d-out-blue-raspberry-10-58-oz-300-g/130111","title":"ALR Industries, Chain'D Out, Blue Raspberry, 10.58 oz (300 g)","weight":"299.94 g","quantity":"\n                            <span class=\"product-weight\">\n                                    <span class=\"toggle-weight-preference\" name=\"wpc\" data-current-wpc=\"2\" data-imperial=\"6.15 x 3.7 x 3.7 in, 0.85 lb\" data-metric=\"15.6 x 9.4 x 9.4 cm, 0.39 kg\">15.6 x 9.4 x 9.4 cm, 0.39 kg</span>\n                            </span>\n                        ","priceUs":"$27.95","dimensions":"5.3 x 5.3 x 9.4 cm, 0.14 kg","expiryDate":"undefined undefined","rating":"1,202"},{"firstImage":"https://cloudinary.images-iherb.com/image/upload/f_auto,q_auto:eco/images/ahp/ahp00030/u/13.jpg","popularity":10,"productUrl":"https://www.iherb.com/pr/alr-industries-chain-d-out-lemon-lime-10-58-oz-300-g/130112","title":"ALR Industries, Chain'd Out, Lemon-Lime , 10.58 oz (300 g)","weight":"299.94 g","quantity":"\n                            <span class=\"product-weight\">\n                                    <span class=\"toggle-weight-preference\" name=\"wpc\" data-current-wpc=\"2\" data-imperial=\"6.15 x 3.7 x 3.7 in, 0.85 lb\" data-metric=\"15.6 x 9.4 x 9.4 cm, 0.39 kg\">15.6 x 9.4 x 9.4 cm, 0.39 kg</span>\n                            </span>\n                        ","priceUs":"$27.95","dimensions":"18.7 x 9.8 x 5.3 cm, 0.09 kg","expiryDate":"undefined undefined","rating":"20"},{"firstImage":"https://cloudinary.images-iherb.com/image/upload/f_auto,q_auto:eco/images/lte/lte01006/u/7.jpg","popularity":11,"productUrl":"https://www.iherb.com/pr/alta-health-magnesium-chloride-100-tablets/10682","title":"Alta Health, Magnesium Chloride, 100 Tablets","weight":"0.11 kg","quantity":"100 Count","priceUs":"$15.17","dimensions":"8.9 x 8.5 x 7.2 cm, 0.16 kg","expiryDate":"undefined undefined","rating":"23"},{"firstImage":"https://cloudinary.images-iherb.com/image/upload/f_auto,q_auto:eco/images/lte/lte01050/u/13.jpg","popularity":12,"productUrl":"https://www.iherb.com/pr/alta-health-herbal-silica-with-bioflavonoids-120-tablets/5683","title":"Alta Health, Herbal Silica with Bioflavonoids, 120 Tablets","weight":"0.14 kg","quantity":"120 Count","priceUs":"$24.48","dimensions":"9.7 x 7.1 x 5.2 cm, 0.09 kg","expiryDate":"undefined undefined","rating":"2,234"},{"firstImage":"https://cloudinary.images-iherb.com/image/upload/f_auto,q_auto:eco/images/lte/lte01048/u/15.jpg","popularity":13,"productUrl":"https://www.iherb.com/pr/alta-health-potassium-chloride-plus-silica-100-capsules/9134","title":"Alta Health, Potassium Chloride, Plus Silica, 100 Capsules","weight":"0.19 kg","quantity":"100 Count","priceUs":"$16.14","dimensions":"15.7 x 7.9 x 1 cm, 0.09 kg","expiryDate":"undefined undefined","rating":"24"},{"firstImage":"https://cloudinary.images-iherb.com/image/upload/f_auto,q_auto:eco/images/lte/lte01049/u/9.jpg","popularity":14,"productUrl":"https://www.iherb.com/pr/alta-health-can-gest-a-natural-digestive-aid-4-oz/12389","title":"Alta Health, Can-Gest, A Natural Digestive Aid, 4 oz","weight":"0.16 kg","quantity":"113.4 g","priceUs":"$22.02","dimensions":"7.9 x 0.8 x 16 cm, 0.09 kg","expiryDate":"undefined undefined","rating":"27"},{"firstImage":"https://cloudinary.images-iherb.com/image/upload/f_auto,q_auto:eco/images/lte/lte01256/u/3.jpg","popularity":15,"productUrl":"https://www.iherb.com/pr/alta-health-can-gest-natural-digestive-aid-100-capsules/13009","title":"Alta Health, Can-Gest, Natural Digestive Aid, 100 Capsules","weight":"0.09 kg","quantity":"100 Count","priceUs":"$19.09","dimensions":"16.1 x 7.9 x 1 cm, 0.09 kg","expiryDate":"undefined undefined","rating":"41"},{"firstImage":"https://cloudinary.images-iherb.com/image/upload/f_auto,q_auto:eco/images/lte/lte01255/u/3.jpg","popularity":16,"productUrl":"https://www.iherb.com/pr/alter-eco-organic-dark-chocolate-bar-classic-blackout-85-cocoa-2-82-oz-80-g/46389","title":"Alter Eco, Organic Dark Chocolate Bar, Classic Blackout, 85% Cocoa, 2.82 oz (80 g)","weight":"0.09 kg","quantity":"79.95 g","priceUs":"$3.51","dimensions":"0.8 x 7.9 x 16.3 cm, 0.09 kg","expiryDate":"July 2025","rating":"38"},{"popularity":17,"productUrl":"https://www.iherb.com/pr/alter-eco-organic-dark-chocolate-bar-burnt-caramel-70-cacao-2-82-oz-80-g/63451","title":"Alter Eco, Organic Dark Chocolate Bar, Burnt Caramel, 70% Cacao, 2.82 oz (80 g)","weight":"0.09 kg","quantity":"79.95 g","priceUs":"$3.51","dimensions":"16 x 8 x 1.1 cm, 0.09 kg","expiryDate":"September 2024","rating":"37"},{"popularity":18,"productUrl":"https://www.iherb.com/pr/alter-eco-organic-dark-chocolate-bar-sea-salt-70-cacao-2-82-oz-80-g/61817","title":"Alter Eco, Organic Dark Chocolate Bar, Sea Salt, 70% Cacao, 2.82 oz (80 g)","weight":"0.09 kg","quantity":"79.95 g","priceUs":"$3.51","dimensions":"16 x 8.4 x 1.1 cm, 0.09 kg","expiryDate":"January 2025","rating":"77"},{"popularity":19,"productUrl":"https://www.iherb.com/pr/alter-eco-organic-dark-chocolate-brown-butter-70-cacao-2-82-oz-80-g/61816","title":"Alter Eco, Organic Dark Chocolate,  Brown Butter, 70% Cacao, 2.82 oz (80 g)","weight":"0.09 kg","quantity":"79.95 g","priceUs":"$3.51","dimensions":"1 x 8.1 x 16 cm, 0.09 kg","expiryDate":"July 2024","rating":"55"},{"popularity":20,"productUrl":"https://www.iherb.com/pr/alter-eco-organic-dark-chocolate-bar-almond-blackout-85-cacao-2-65-oz-75-g/132531","title":"Alter Eco, Organic Dark Chocolate Bar, Almond Blackout, 85% Cacao, 2.65 oz (75 g)","weight":"0.09 kg","quantity":"75.13 g","priceUs":"$4.03","dimensions":"16.1 x 8.1 x 1 cm, 0.09 kg","expiryDate":"May 2024","rating":"46"},{"popularity":21,"productUrl":"https://www.iherb.com/pr/alter-eco-organic-dark-chocolate-bar-orange-blackout-85-cacao-2-65-oz-75-g/132532","title":"Alter Eco, Organic Dark Chocolate Bar, Orange Blackout, 85% Cacao, 2.65 oz (75 g)","weight":"0.09 kg","quantity":"75.13 g","priceUs":"$4.03","dimensions":"16.3 x 8 x 1.1 cm, 0.09 kg","expiryDate":"September 2024","rating":"40"},{"popularity":22,"productUrl":"https://www.iherb.com/pr/alter-eco-organic-dark-chocolate-bar-coconut-toffee-47-cacao-2-82-oz-80-g/46391","title":"Alter Eco, Organic Dark Chocolate Bar, Coconut Toffee, 47% Cacao, 2.82 oz (80 g)","weight":"0.09 kg","quantity":"79.95 g","priceUs":"$3.51","dimensions":"16.1 x 8 x 1.1 cm, 0.09 kg","expiryDate":"September 2024","rating":"8"},{"popularity":23,"productUrl":"https://www.iherb.com/pr/alter-eco-truffle-thins-organic-dark-chocolate-bar-mint-creme-2-96-oz-84-g/132533","title":"Alter Eco, Truffle Thins, Organic Dark Chocolate Bar, Mint Creme, 2.96 oz (84 g)","weight":"0.09 kg","quantity":"83.91 g","priceUs":"$4.03","dimensions":"16 x 8 x 1 cm, 0.09 kg","expiryDate":"July 2024","rating":"379"},{"popularity":24,"productUrl":"https://www.iherb.com/pr/alter-eco-organic-dark-chocolate-bar-mint-blackout-90-cacao-2-65-oz-75-g/132525","title":"Alter Eco, Organic Dark Chocolate Bar, Mint Blackout, 90% Cacao, 2.65 oz (75 g)","weight":"0.09 kg","quantity":"75.13 g","priceUs":"$4.03","dimensions":"16 x 8.3 x 1.1 cm, 0.09 kg","expiryDate":"January 2025","rating":"2"},{"popularity":25,"productUrl":"https://www.iherb.com/pr/alter-eco-truffle-thins-organic-dark-chocolate-bar-salted-caramel-2-96-oz-84-g/132534","title":"Alter Eco, Truffle Thins, Organic Dark Chocolate Bar, Salted Caramel, 2.96 oz (84 g)","weight":"0.09 kg","quantity":"83.91 g","priceUs":"$4.03","dimensions":"16 x 8.1 x 1 cm, 0.09 kg","expiryDate":"July 2024","rating":"1,861"},{"popularity":26,"productUrl":"https://www.iherb.com/pr/alter-eco-organic-dark-chocolate-bar-raspberry-blackout-85-cacao-2-65-oz-75-g/132529","title":"Alter Eco, Organic Dark Chocolate Bar, Raspberry Blackout, 85% Cacao, 2.65 oz (75 g)","weight":"0.09 kg","quantity":"75.13 g","priceUs":"$4.03","dimensions":"16.1 x 8.3 x 1 cm, 0.09 kg","expiryDate":"September 2024","rating":"860"},{"popularity":27,"productUrl":"https://www.iherb.com/pr/alter-eco-truffle-thins-organic-dark-chocolate-bar-classic-dark-2-96-oz-84-g/132535","title":"Alter Eco, Truffle Thins, Organic Dark Chocolate Bar, Classic Dark, 2.96 oz (84 g)","weight":"0.09 kg","quantity":"75.13 g","priceUs":"$4.03","dimensions":"16.1 x 9 x 1 cm, 0.09 kg","expiryDate":"June 2024","rating":"708"},{"popularity":28,"productUrl":"https://www.iherb.com/pr/alter-eco-organic-dark-chocolate-bar-salt-malt-70-cacao-2-82-oz-80-g/73328","title":"Alter Eco, Organic Dark Chocolate Bar, Salt &amp; Malt, 70% Cacao, 2.82 oz (80 g)","weight":"0.09 kg","quantity":"79.95 g","priceUs":"$4.03","dimensions":"16.1 x 8.1 x 1.1 cm, 0.09 kg","expiryDate":"November 2024","rating":"821"},{"popularity":29,"productUrl":"https://www.iherb.com/pr/alter-eco-truffle-thins-organic-dark-chocolate-bar-cr-me-br-l-e-2-96-oz-84-g/132536","title":"Alter Eco, Truffle Thins, Organic Dark Chocolate Bar, Crème Brûlée, 2.96 oz (84 g)","weight":"0.09 kg","quantity":"83.91 g","priceUs":"$4.03","dimensions":"17.4 x 15.2 x 6.9 cm, 0.23 kg","expiryDate":"August 2024","rating":"9"},{"popularity":30,"productUrl":"https://www.iherb.com/pr/alter-eco-truffle-thins-organic-dark-chocolate-bar-raspberry-cr-me-2-96-oz-84-g/132537","title":"Alter Eco, Truffle Thins, Organic Dark Chocolate Bar, Raspberry Crème, 2.96 oz (84 g)","weight":"0.09 kg","quantity":"83.91 g","priceUs":"$4.03","dimensions":"16 x 8 x 1.1 cm, 0.09 kg","expiryDate":"July 2024","rating":"639"},{"popularity":31,"productUrl":"https://www.iherb.com/pr/alter-eco-truffle-thins-organic-dark-chocolate-bar-orange-cr-me-2-96-oz-84-g/132538","title":"Alter Eco, Truffle Thins, Organic Dark Chocolate Bar, Orange Crème, 2.96 oz (84 g)","weight":"0.09 kg","quantity":"75.13 g","priceUs":"$4.03","dimensions":"16.5 x 11.6 x 5.3 cm, 0.23 kg","expiryDate":"July 2024","rating":"147"},{"popularity":32,"productUrl":"https://www.iherb.com/pr/alter-eco-organic-granola-cashew-butter-8-oz-227-g/134482","title":"Alter Eco, Organic Granola, Cashew Butter, 8 oz (227 g)","weight":"0.36 kg","quantity":"226.8 g","priceUs":"$6.85","dimensions":"16 x 7.9 x 1 cm, 0.08 kg","expiryDate":"August 2024","rating":"5"},{"popularity":33,"productUrl":"https://www.iherb.com/pr/alter-eco-organic-dark-chocolate-bar-quinoa-crunch-60-cacao-2-82-oz-80-g/46383","title":"Alter Eco, Organic Dark Chocolate Bar, Quinoa Crunch, 60% Cacao, 2.82 oz (80 g)","weight":"0.09 kg","quantity":"79.95 g","priceUs":"$4.03","dimensions":"10.2 x 4.6 x 18.5 cm, 0.14 kg","expiryDate":"January 2025"},{"popularity":34,"productUrl":"https://www.iherb.com/pr/alter-eco-organic-granola-cinnamon-raisin-8-oz-227-g/134481","title":"Alter Eco, Organic Granola, Cinnamon Raisin, 8 oz (227 g)","weight":"0.23 kg","quantity":"226.8 g","priceUs":"$6.85","expiryDate":"June 2024"},{"popularity":35,"productUrl":"https://www.iherb.com/pr/alter-eco-organic-dark-chocolate-bar-super-blackout-90-cacao-2-65-oz-75-g/73330","title":"Alter Eco, Organic Dark Chocolate Bar, Super Blackout, 90% Cacao, 2.65 oz (75 g)","weight":"0.08 kg","quantity":"75.13 g","priceUs":"$3.51","expiryDate":"March 2025"},{"popularity":36,"productUrl":"https://www.iherb.com/pr/alter-eco-organic-dark-milk-chocolate-silk-velvet-truffles-4-2-oz-120-g/56336","title":"Alter Eco, Organic Dark Milk Chocolate, Silk Velvet Truffles, 4.2 oz (120 g)","weight":"0.17 kg","quantity":"10 Count","priceUs":"$7.73","expiryDate":"August 2024"},{"popularity":37,"productUrl":"https://www.iherb.com/pr/alter-eco-organic-salted-caramel-truffles-dark-chocolate-10-individually-wrapped-truffles/61819","title":"Alter Eco, Organic Salted Caramel Truffles, Dark Chocolate, 10 Individually Wrapped Truffles","weight":"119.07 g","quantity":"\n                            <span class=\"product-weight\">\n                                    <span class=\"toggle-weight-preference\" name=\"wpc\" data-current-wpc=\"2\" data-imperial=\"1.9 x 4 x 7.3 in, 0.35 lb\" data-metric=\"4.8 x 10.2 x 18.5 cm, 0.16 kg\">4.8 x 10.2 x 18.5 cm, 0.16 kg</span>\n                            </span>\n                        ","priceUs":"$7.73","expiryDate":"undefined undefined"},{"popularity":38,"productUrl":"https://www.iherb.com/pr/alter-eco-organic-classic-dark-truffles-dark-chocolate-4-2-oz-120-g/56335","title":"Alter Eco, Organic Classic Dark Truffles, Dark Chocolate, 4.2 oz (120 g)","weight":"119.07 g","quantity":"\n                            <span class=\"product-weight\">\n                                    <span class=\"toggle-weight-preference\" name=\"wpc\" data-current-wpc=\"2\" data-imperial=\"7.2 x 4 x 1.8 in, 0.31 lb\" data-metric=\"18.3 x 10.2 x 4.6 cm, 0.14 kg\">18.3 x 10.2 x 4.6 cm, 0.14 kg</span>\n                            </span>\n                        ","priceUs":"$7.73","expiryDate":"undefined undefined"},{"popularity":39,"productUrl":"https://www.iherb.com/pr/alter-eco-organic-granola-dark-chocolate-8-oz-227-g/134483","title":"Alter Eco, Organic Granola, Dark Chocolate, 8 oz (227 g)","weight":"226.8 g","quantity":"\n                            <span class=\"product-weight\">\n                                    <span class=\"toggle-weight-preference\" name=\"wpc\" data-current-wpc=\"2\" data-imperial=\"6.35 x 4.8 x 2.85 in, 0.5 lb\" data-metric=\"16.1 x 12.2 x 7.2 cm, 0.23 kg\">16.1 x 12.2 x 7.2 cm, 0.23 kg</span>\n                            </span>\n                        ","priceUs":"$6.85","expiryDate":"undefined undefined"},{"popularity":40,"productUrl":"https://www.iherb.com/pr/alter-eco-organic-dark-chocolate-truffles-sea-salt-10-truffles-4-2-oz-120-g/61818","title":"Alter Eco, Organic Dark Chocolate Truffles, Sea Salt, 10 Truffles, 4.2 oz (120 g)","weight":"119.07 g","quantity":"\n                            <span class=\"product-weight\">\n                                    <span class=\"toggle-weight-preference\" name=\"wpc\" data-current-wpc=\"2\" data-imperial=\"1.9 x 4 x 7.3 in, 0.35 lb\" data-metric=\"4.8 x 10.2 x 18.5 cm, 0.16 kg\">4.8 x 10.2 x 18.5 cm, 0.16 kg</span>\n                            </span>\n                        ","priceUs":"$7.73","expiryDate":"undefined undefined"},{"popularity":41,"productUrl":"https://www.iherb.com/pr/alter-eco-organic-mint-creme-truffles-dark-chocolate-4-2-oz-120-g/73331","title":"Alter Eco, Organic Mint Creme Truffles, Dark Chocolate, 4.2 oz (120 g)","weight":"119.07 g","quantity":"\n                            <span class=\"product-weight\">\n                                    <span class=\"toggle-weight-preference\" name=\"wpc\" data-current-wpc=\"2\" data-imperial=\"6.75 x 4.05 x 1.6 in, 0.3 lb\" data-metric=\"17.1 x 10.3 x 4.1 cm, 0.14 kg\">17.1 x 10.3 x 4.1 cm, 0.14 kg</span>\n                            </span>\n                        ","priceUs":"$8.88","expiryDate":"undefined undefined"},{"popularity":42,"productUrl":"https://www.iherb.com/pr/alter-eco-organic-chocolate-bar-classic-grass-fed-milk-2-65-oz-75-g/132526","title":"Alter Eco, Organic Chocolate Bar, Classic Grass Fed Milk, 2.65 oz (75 g)","weight":"75.13 g","quantity":"\n                            <span class=\"product-weight\">\n                                    <span class=\"toggle-weight-preference\" name=\"wpc\" data-current-wpc=\"2\" data-imperial=\"6.4 x 3.15 x 0.4 in, 0.2 lb\" data-metric=\"16.3 x 8 x 1 cm, 0.09 kg\">16.3 x 8 x 1 cm, 0.09 kg</span>\n                            </span>\n                        ","priceUs":"$4.03","expiryDate":"undefined undefined"},{"popularity":43,"productUrl":"https://www.iherb.com/pr/alter-eco-organic-chocolate-bar-almond-grass-fed-milk-2-65-oz-75-g/132527","title":"Alter Eco, Organic Chocolate Bar, Almond Grass Fed Milk, 2.65 oz (75 g)","weight":"75.13 g","quantity":"\n                            <span class=\"product-weight\">\n                                    <span class=\"toggle-weight-preference\" name=\"wpc\" data-current-wpc=\"2\" data-imperial=\"6.35 x 3.2 x 0.45 in, 0.15 lb\" data-metric=\"16.1 x 8.1 x 1.1 cm, 0.07 kg\">16.1 x 8.1 x 1.1 cm, 0.07 kg</span>\n                            </span>\n                        ","priceUs":"$4.03","expiryDate":"undefined undefined"},{"popularity":44,"productUrl":"https://www.iherb.com/pr/alter-eco-organic-chocolate-bar-rice-crisp-grass-fed-milk-2-65-oz-75-g/132528","title":"Alter Eco, Organic Chocolate Bar, Rice Crisp Grass Fed Milk, 2.65 oz (75 g)","weight":"75.13 g","quantity":"\n                            <span class=\"product-weight\">\n                                    <span class=\"toggle-weight-preference\" name=\"wpc\" data-current-wpc=\"2\" data-imperial=\"6.3 x 3.15 x 0.45 in, 0.2 lb\" data-metric=\"16 x 8 x 1.1 cm, 0.09 kg\">16 x 8 x 1.1 cm, 0.09 kg</span>\n                            </span>\n                        ","priceUs":"$4.03","expiryDate":"undefined undefined"},{"popularity":45,"productUrl":"https://www.iherb.com/pr/alter-eco-organic-dark-chocolate-bar-total-blackout-100-cacao-2-65-oz-75-g/132530","title":"Alter Eco, Organic Dark Chocolate Bar, Total Blackout, 100% Cacao, 2.65 oz (75 g)","weight":"75.13 g","quantity":"\n                            <span class=\"product-weight\">\n                                    <span class=\"toggle-weight-preference\" name=\"wpc\" data-current-wpc=\"2\" data-imperial=\"6.35 x 3.15 x 0.45 in, 0.2 lb\" data-metric=\"16.1 x 8 x 1.1 cm, 0.09 kg\">16.1 x 8 x 1.1 cm, 0.09 kg</span>\n                            </span>\n                        ","priceUs":"$4.03","expiryDate":"undefined undefined"},{"popularity":46,"productUrl":"https://www.iherb.com/pr/alter-eco-organic-dark-chocolate-truffles-superdark-80-cacao-10-truffles-4-2-oz-120-g/132539","title":"Alter Eco, Organic Dark Chocolate Truffles, Superdark, 80% Cacao, 10 Truffles, 4.2 oz (120 g)","weight":"119.07 g","quantity":"\n                            <span class=\"product-weight\">\n                                    <span class=\"toggle-weight-preference\" name=\"wpc\" data-current-wpc=\"2\" data-imperial=\"6.75 x 4.05 x 1.75 in, 0.3 lb\" data-metric=\"17.1 x 10.3 x 4.4 cm, 0.14 kg\">17.1 x 10.3 x 4.4 cm, 0.14 kg</span>\n                            </span>\n                        ","priceUs":"$8.88","expiryDate":"undefined undefined"}]